{
  "updatedAt": "2026-06-25T22:21:47.186Z",
  "games": {
    "apocalypse": {
      "placeId": "90148635862803",
      "universeId": 9098570654,
      "name": "[UPD] 🧟 Survive the Apocalypse",
      "visits": 178241084,
      "playing": 13510,
      "favorites": 275648,
      "creatorName": "Rubicon South",
      "creatorVerified": true
    },
    "prospecting": {
      "placeId": "129827112113663",
      "universeId": 7629331599,
      "name": "[🌞EVENT] Prospecting! 💎",
      "visits": 242025480,
      "playing": 5101,
      "favorites": 420547,
      "creatorName": "Prospecting!",
      "creatorVerified": true
    },
    "parkour": {
      "placeId": "75034791252172",
      "universeId": 9871986464,
      "name": "[UPD] Parkour For Brainrots!",
      "visits": 51202809,
      "playing": 257,
      "favorites": 70294,
      "creatorName": "Fly To 8 Figs",
      "creatorVerified": false
    },
    "restaurant": {
      "placeId": "77843161404023",
      "universeId": 9970645639,
      "name": "Run a Restaurant!",
      "visits": 45870671,
      "playing": 16811,
      "favorites": 393391,
      "creatorName": "Burnt Toast Labs!",
      "creatorVerified": true
    },
    "burgerz": {
      "placeId": "99817148924004",
      "universeId": 7498898979,
      "name": "Burgerz🍔",
      "visits": 54112222,
      "playing": 3720,
      "favorites": 169271,
      "creatorName": "2 Player Games!",
      "creatorVerified": true
    },
    "gag2": {
      "placeId": "97598239454123",
      "universeId": 10200395747,
      "name": "Grow a Garden 2",
      "visits": 666280543,
      "playing": 462733,
      "favorites": 494941,
      "creatorName": "Strawberreh Squad",
      "creatorVerified": true
    }
  }
}
